{"id": "0024", "title": "Crucigrama #24", "difficulty": 2, "rows": 11, "cols": 11, "mask": [[false, false, false, false, false, false, true, false, false, false, false], [false, false, false, false, false, false, true, false, false, false, false], [false, false, false, false, false, false, true, false, false, false, false], [false, false, false, true, false, false, false, true, false, false, false], [false, false, false, true, false, false, false, true, false, false, false], [false, false, false, false, true, true, false, false, false, false, false], [true, true, true, false, false, false, false, false, true, true, true], [false, false, false, false, false, false, true, false, false, false, false], [false, false, false, true, false, false, false, true, false, false, false], [false, false, false, true, false, false, false, true, false, false, false], [false, false, false, true, false, false, false, true, false, false, false]], "solution": [["A", "G", "R", "U", "R", "A", "", "A", "F", "T", "A"], ["T", "R", "E", "P", "A", "R", "", "V", "I", "A", "S"], ["R", "E", "N", "D", "I", "R", "", "E", "S", "T", "E"], ["A", "D", "A", "", "T", "I", "A", "", "T", "A", "N"], ["C", "A", "N", "", "A", "A", "L", "", "O", "M", "S"], ["O", "L", "O", "R", "", "", "T", "U", "L", "I", "O"], ["", "", "", "E", "N", "R", "A", "S", "", "", ""], ["B", "O", "N", "S", "A", "I", "", "O", "C", "C", "A"], ["O", "R", "A", "", "T", "A", "S", "", "A", "A", "M"], ["S", "E", "D", "", "A", "D", "E", "", "T", "O", "P"], ["C", "O", "A", "", "L", "A", "R", "", "A", "N", "O"]], "numbers": {"0,0": 1, "0,1": 2, "0,2": 3, "0,3": 4, "0,4": 5, "0,5": 6, "0,7": 7, "0,8": 8, "0,9": 9, "0,10": 10, "1,0": 11, "1,7": 12, "2,0": 13, "2,7": 14, "3,0": 15, "3,4": 16, "3,6": 17, "3,8": 18, "4,0": 19, "4,4": 20, "4,8": 21, "5,0": 22, "5,3": 23, "5,6": 24, "5,7": 25, "6,3": 26, "6,4": 27, "6,5": 28, "7,0": 29, "7,1": 30, "7,2": 31, "7,7": 32, "7,8": 33, "7,9": 34, "7,10": 35, "8,0": 36, "8,4": 37, "8,6": 38, "8,8": 39, "9,0": 40, "9,4": 41, "9,8": 42, "10,0": 43, "10,4": 44, "10,8": 45}, "clues_h": [{"num": 1, "word": "AGRURA", "clue": "Sabor agre, agrio, acre o ácido (fuerte, áspero y agresivo)"}, {"num": 7, "word": "AFTA", "clue": "Pequeña lesión o úlcera mucosa que afecta la boca, lengua o labios"}, {"num": 11, "word": "TREPAR", "clue": "Escalar o subir por alguna superficie casi vertical, ayudándose con pies y manos a través de sus hendiduras y salientes"}, {"num": 12, "word": "VIAS", "clue": "Mandatos o leyes bíblicas"}, {"num": 13, "word": "RENDIR", "clue": "Dicho de un estudiante: someterse a examen"}, {"num": 14, "word": "ESTE", "clue": "Se emplea para indicar o señalar algo o a alguien próximo al hablante, o referirse a algo que se acaba de mencionar"}, {"num": 15, "word": "ADA", "clue": "Nombre de pila de mujer"}, {"num": 16, "word": "TIA", "clue": "Hermana de la madre o del padre de una persona"}, {"num": 18, "word": "TAN", "clue": "Variante de tanto"}, {"num": 19, "word": "CAN", "clue": "(Canis lupus) Variedad doméstica del lobo, que por su prolongada crianza y selección por el hombre ha dado muchas y diversas razas"}, {"num": 20, "word": "AAL", "clue": "Fruto de esta planta, consumido como alimento o empleado como medicina"}, {"num": 21, "word": "OMS", "clue": "Organismo de la organización de las Naciones Unidas (ONU) especializado en gestionar políticas de prevención, promoción e intervención en salud a nivel mundial"}, {"num": 22, "word": "OLOR", "clue": "Conjunto de sensaciones captadas por el sentido del olfato, cuando en la nariz entran las emanaciones transportadas por el aire o por algún líquido"}, {"num": 24, "word": "TULIO", "clue": "Elemento químico de la tabla periódica cuyo símbolo es Tm y su número atómico es 69. Pertenece al grupo de los lantánidos"}, {"num": 26, "word": "ENRAS", "clue": "La superficie inferior de todo sillar ó dovela, con la cual toca la que tiene debajo"}, {"num": 29, "word": "BONSAI", "clue": "Arte de cultivar árboles y plantas, normalmente arbustos, controlando su tamaño para que permanezcan de un tamaño muy inferior al natural"}, {"num": 32, "word": "OCCA", "clue": "Rastrillo que se usa para deshacer los terrones"}, {"num": 36, "word": "ORA", "clue": "Variante informal de ahora (en este momento, dentro de poco tiempo, hace poco tiempo, unas veces y otras)"}, {"num": 37, "word": "TAS", "clue": "Yunque de platero"}, {"num": 39, "word": "AAM", "clue": "Antigua medida de líquidos usada en Ámsterdam que contiene 128 mingles"}, {"num": 40, "word": "SED", "clue": "Por extensión, deseo profundo e impulsivo de alguna cosa"}, {"num": 41, "word": "ADE", "clue": "Bebida endulzada de zumo de fruta diluido"}, {"num": 42, "word": "TOP", "clue": "Dicho de una cosa: de alto nivel, principal, que tiene el primer lugar de estimación o importancia"}, {"num": 43, "word": "COA", "clue": "Instrumento de labranza, similar en su forma a un palo"}, {"num": 44, "word": "LAR", "clue": "Cada una de las deidades romanas que protegían el hogar y la familia"}, {"num": 45, "word": "ANO", "clue": "(Crotophaga ani) Garrapatero aní"}], "clues_v": [{"num": 1, "word": "ATRACO", "clue": "Acción o efecto de atracar"}, {"num": 2, "word": "GREDAL", "clue": "Cantera para extraer creta"}, {"num": 3, "word": "RENANO", "clue": "Se dice de algo que proviene o tiene relación con"}, {"num": 4, "word": "UPD", "clue": "Fiesta que se realiza antes de tener el último primer día de la escuela secundaria"}, {"num": 5, "word": "RAITA", "clue": "Acompañamiento indio de yogur, pepinos picados y especias"}, {"num": 6, "word": "ARRIA", "clue": "Grupo de animales de tiro que van juntos y conducidos por los arrieros o trajinantes"}, {"num": 7, "word": "AVE", "clue": "Dícese de la carne de estos animales empleada como alimento, especialmente la de pollo, gallina, pato, pavo o perdiz"}, {"num": 8, "word": "FISTOL", "clue": "Alfiler empleado como adorno en las corbatas"}, {"num": 9, "word": "TATAMI", "clue": "Estera utilizada para recubrir el piso en las casas tradicionales japonesas, que por lo general es de paja"}, {"num": 10, "word": "ASENSO", "clue": "Acción o efecto de asentir, estar de acuerdo o creer"}, {"num": 17, "word": "ALTA", "clue": "En los hospitales, orden informada al enfermo a quien se da por sano, para regresar a su vida normal"}, {"num": 23, "word": "RES", "clue": "Cabeza de ganado o de caza mayor, especialmente considerado en cuanto a su aprovechamiento alimentario o económico"}, {"num": 25, "word": "USO", "clue": "Acción o efecto de usar o de usarse"}, {"num": 27, "word": "NATAL", "clue": "Relativo al nacimiento"}, {"num": 28, "word": "RIADA", "clue": "Aumento repentino del caudal de un río o arroyo"}, {"num": 29, "word": "BOSC", "clue": "Pera amarilla verdosa"}, {"num": 30, "word": "OREO", "clue": "Refrigeración forzada a la que se somete una canal, media canal o cuarto de canal de vacuno inmediatamente después del sacrificio y faenado"}, {"num": 31, "word": "NADA", "clue": "Fenómeno contrario al ser, ausencia total de las cosas"}, {"num": 33, "word": "CATA", "clue": "Acción o efecto de catar"}, {"num": 34, "word": "CAON", "clue": "Que tiene relación de amistad"}, {"num": 35, "word": "AMPO", "clue": "Copo de nieve"}, {"num": 38, "word": "SER", "clue": "Tener algo una determinada naturaleza, propiedad o cualidad estable"}], "slots": [{"dir": "H", "num": 1, "cells": [[0, 0], [0, 1], [0, 2], [0, 3], [0, 4], [0, 5]]}, {"dir": "H", "num": 7, "cells": [[0, 7], [0, 8], [0, 9], [0, 10]]}, {"dir": "H", "num": 11, "cells": [[1, 0], [1, 1], [1, 2], [1, 3], [1, 4], [1, 5]]}, {"dir": "H", "num": 12, "cells": [[1, 7], [1, 8], [1, 9], [1, 10]]}, {"dir": "H", "num": 13, "cells": [[2, 0], [2, 1], [2, 2], [2, 3], [2, 4], [2, 5]]}, {"dir": "H", "num": 14, "cells": [[2, 7], [2, 8], [2, 9], [2, 10]]}, {"dir": "H", "num": 15, "cells": [[3, 0], [3, 1], [3, 2]]}, {"dir": "H", "num": 16, "cells": [[3, 4], [3, 5], [3, 6]]}, {"dir": "H", "num": 18, "cells": [[3, 8], [3, 9], [3, 10]]}, {"dir": "H", "num": 19, "cells": [[4, 0], [4, 1], [4, 2]]}, {"dir": "H", "num": 20, "cells": [[4, 4], [4, 5], [4, 6]]}, {"dir": "H", "num": 21, "cells": [[4, 8], [4, 9], [4, 10]]}, {"dir": "H", "num": 22, "cells": [[5, 0], [5, 1], [5, 2], [5, 3]]}, {"dir": "H", "num": 24, "cells": [[5, 6], [5, 7], [5, 8], [5, 9], [5, 10]]}, {"dir": "H", "num": 26, "cells": [[6, 3], [6, 4], [6, 5], [6, 6], [6, 7]]}, {"dir": "H", "num": 29, "cells": [[7, 0], [7, 1], [7, 2], [7, 3], [7, 4], [7, 5]]}, {"dir": "H", "num": 32, "cells": [[7, 7], [7, 8], [7, 9], [7, 10]]}, {"dir": "H", "num": 36, "cells": [[8, 0], [8, 1], [8, 2]]}, {"dir": "H", "num": 37, "cells": [[8, 4], [8, 5], [8, 6]]}, {"dir": "H", "num": 39, "cells": [[8, 8], [8, 9], [8, 10]]}, {"dir": "H", "num": 40, "cells": [[9, 0], [9, 1], [9, 2]]}, {"dir": "H", "num": 41, "cells": [[9, 4], [9, 5], [9, 6]]}, {"dir": "H", "num": 42, "cells": [[9, 8], [9, 9], [9, 10]]}, {"dir": "H", "num": 43, "cells": [[10, 0], [10, 1], [10, 2]]}, {"dir": "H", "num": 44, "cells": [[10, 4], [10, 5], [10, 6]]}, {"dir": "H", "num": 45, "cells": [[10, 8], [10, 9], [10, 10]]}, {"dir": "V", "num": 1, "cells": [[0, 0], [1, 0], [2, 0], [3, 0], [4, 0], [5, 0]]}, {"dir": "V", "num": 29, "cells": [[7, 0], [8, 0], [9, 0], [10, 0]]}, {"dir": "V", "num": 2, "cells": [[0, 1], [1, 1], [2, 1], [3, 1], [4, 1], [5, 1]]}, {"dir": "V", "num": 30, "cells": [[7, 1], [8, 1], [9, 1], [10, 1]]}, {"dir": "V", "num": 3, "cells": [[0, 2], [1, 2], [2, 2], [3, 2], [4, 2], [5, 2]]}, {"dir": "V", "num": 31, "cells": [[7, 2], [8, 2], [9, 2], [10, 2]]}, {"dir": "V", "num": 4, "cells": [[0, 3], [1, 3], [2, 3]]}, {"dir": "V", "num": 23, "cells": [[5, 3], [6, 3], [7, 3]]}, {"dir": "V", "num": 5, "cells": [[0, 4], [1, 4], [2, 4], [3, 4], [4, 4]]}, {"dir": "V", "num": 27, "cells": [[6, 4], [7, 4], [8, 4], [9, 4], [10, 4]]}, {"dir": "V", "num": 6, "cells": [[0, 5], [1, 5], [2, 5], [3, 5], [4, 5]]}, {"dir": "V", "num": 28, "cells": [[6, 5], [7, 5], [8, 5], [9, 5], [10, 5]]}, {"dir": "V", "num": 17, "cells": [[3, 6], [4, 6], [5, 6], [6, 6]]}, {"dir": "V", "num": 38, "cells": [[8, 6], [9, 6], [10, 6]]}, {"dir": "V", "num": 7, "cells": [[0, 7], [1, 7], [2, 7]]}, {"dir": "V", "num": 25, "cells": [[5, 7], [6, 7], [7, 7]]}, {"dir": "V", "num": 8, "cells": [[0, 8], [1, 8], [2, 8], [3, 8], [4, 8], [5, 8]]}, {"dir": "V", "num": 33, "cells": [[7, 8], [8, 8], [9, 8], [10, 8]]}, {"dir": "V", "num": 9, "cells": [[0, 9], [1, 9], [2, 9], [3, 9], [4, 9], [5, 9]]}, {"dir": "V", "num": 34, "cells": [[7, 9], [8, 9], [9, 9], [10, 9]]}, {"dir": "V", "num": 10, "cells": [[0, 10], [1, 10], [2, 10], [3, 10], [4, 10], [5, 10]]}, {"dir": "V", "num": 35, "cells": [[7, 10], [8, 10], [9, 10], [10, 10]]}]}