{"id": "0070", "title": "Crucigrama #70", "difficulty": 3, "rows": 14, "cols": 14, "mask": [[false, false, false, false, false, true, false, false, false, false, false, false, false, false], [false, false, false, false, false, true, false, false, false, false, false, false, false, false], [false, false, false, false, false, true, false, false, false, false, false, false, false, false], [false, false, false, false, true, false, false, false, false, false, false, true, true, true], [false, false, false, false, true, false, false, false, false, true, false, false, false, false], [false, false, false, true, false, false, false, true, false, false, false, false, false, false], [false, false, false, false, false, false, false, false, true, false, false, false, false, false], [true, true, true, false, false, false, true, false, false, false, true, false, false, false], [false, false, false, false, false, true, false, false, false, false, false, false, false, false], [false, false, false, false, false, true, false, false, false, true, false, false, false, false], [false, false, false, false, true, false, false, false, false, false, false, true, true, true], [false, false, false, false, false, false, true, false, false, false, false, false, false, false], [false, false, false, false, false, false, true, false, false, false, false, false, false, false], [false, false, false, false, false, false, true, false, false, false, false, false, false, false]], "solution": [["M", "A", "M", "B", "O", "", "C", "A", "P", "A", "C", "E", "T", "E"], ["A", "C", "I", "A", "R", "", "A", "C", "A", "L", "O", "R", "A", "R"], ["C", "A", "N", "T", "O", "", "C", "R", "I", "A", "D", "E", "R", "O"], ["A", "B", "U", "E", "", "C", "H", "O", "R", "L", "A", "", "", ""], ["D", "A", "T", "A", "", "A", "U", "N", "A", "", "S", "P", "A", "M"], ["A", "D", "A", "", "W", "I", "Z", "", "R", "O", "T", "O", "S", "O"], ["M", "A", "S", "C", "A", "D", "O", "R", "", "R", "E", "T", "A", "R"], ["", "", "", "A", "R", "O", "", "E", "T", "A", "", "I", "D", "O"], ["T", "E", "R", "N", "A", "", "A", "P", "A", "R", "A", "T", "O", "S"], ["I", "N", "O", "D", "O", "", "T", "O", "P", "", "C", "O", "R", "O"], ["C", "O", "T", "O", "", "A", "E", "R", "I", "T", "O", "", "", ""], ["T", "R", "E", "M", "A", "R", "", "T", "O", "R", "R", "E", "R", "O"], ["A", "M", "A", "B", "L", "E", "", "A", "C", "A", "E", "C", "E", "R"], ["C", "E", "R", "E", "A", "L", "", "R", "A", "P", "S", "O", "D", "A"]], "numbers": {"0,0": 1, "0,1": 2, "0,2": 3, "0,3": 4, "0,4": 5, "0,6": 6, "0,7": 7, "0,8": 8, "0,9": 9, "0,10": 10, "0,11": 11, "0,12": 12, "0,13": 13, "1,0": 14, "1,6": 15, "2,0": 16, "2,6": 17, "3,0": 18, "3,5": 19, "4,0": 20, "4,5": 21, "4,10": 22, "4,11": 23, "4,12": 24, "4,13": 25, "5,0": 26, "5,4": 27, "5,8": 28, "5,9": 29, "6,0": 30, "6,3": 31, "6,7": 32, "6,9": 33, "7,3": 34, "7,7": 35, "7,8": 36, "7,11": 37, "8,0": 38, "8,1": 39, "8,2": 40, "8,6": 41, "8,10": 42, "9,0": 43, "9,6": 44, "9,10": 45, "10,0": 46, "10,5": 47, "10,9": 48, "11,0": 49, "11,4": 50, "11,7": 51, "11,11": 52, "11,12": 53, "11,13": 54, "12,0": 55, "12,7": 56, "13,0": 57, "13,7": 58}, "clues_h": [{"num": 1, "word": "MAMBO", "clue": "Género musical y baile originario de Cuba, con un ritmo sincopado que combina elementos del jazz y ritmos e instrumentos afrocubanos"}, {"num": 6, "word": "CAPACETE", "clue": "Antiguo casco redondo ajustado a la forma de la cabeza que llega hasta la mitad de la frente, usado en el medioevo"}, {"num": 14, "word": "ACIAR", "clue": "Variante de acial"}, {"num": 15, "word": "ACALORAR", "clue": "Dar o causar calor"}, {"num": 16, "word": "CANTO", "clue": "Serie de sonidos modulados de modo armonioso o rítmico por la voz humana"}, {"num": 17, "word": "CRIADERO", "clue": "Sitio destinado en los viveros a la crianza de árboles de todas clases, así como de vides y otras plantas"}, {"num": 18, "word": "ABUE", "clue": "Madre del padre o la madre"}, {"num": 19, "word": "CHORLA", "clue": "Ave similar a la ganga, pero de mayor tamaño"}, {"num": 20, "word": "DATA", "clue": "Nota que indica el lugar y fecha en que algo acontece o se lleva a cabo, en particular como referencia en un documento"}, {"num": 21, "word": "AUNA", "clue": "Juntamente, juntos, a un mismo tiempo"}, {"num": 22, "word": "SPAM", "clue": "Correo electrónico importuno, por lo general de carácter comercial y enviado de forma masiva"}, {"num": 26, "word": "ADA", "clue": "Nombre de pila de mujer"}, {"num": 27, "word": "WIZ", "clue": "Persona con mucha habilidad en algún campo"}, {"num": 28, "word": "ROTOSO", "clue": "Pobre y mal vestido"}, {"num": 30, "word": "MASCADOR", "clue": "Alguien que masca ( especialmente alguien que masca tabaco )"}, {"num": 33, "word": "RETAR", "clue": "Dicho de un noble: acusar ante el rey a otro noble de alevosía, quedando obligado el primero a mantener la denuncia en buena lid"}, {"num": 34, "word": "ARO", "clue": "Pieza de hierro o de otra materia rígida, en figura de circunferencia"}, {"num": 35, "word": "ETA", "clue": "Nombre de la \"e\" larga del alfabeto griego"}, {"num": 37, "word": "IDO", "clue": "Loco, falto de cordura"}, {"num": 38, "word": "TERNA", "clue": "El conjunto de las tres personas que son propuestas a una autoridad para que designe a una de entre ellas en una función o empleo"}, {"num": 41, "word": "APARATOS", "clue": "Instrumento que corrige las irregularidades dentales"}, {"num": 43, "word": "INODO", "clue": "En ciertos sistemas de archivos, estructura de datos que describe las características de un elemento como un archivo o un directorio"}, {"num": 44, "word": "TOP", "clue": "Dicho de una cosa: de alto nivel, principal, que tiene el primer lugar de estimación o importancia"}, {"num": 45, "word": "CORO", "clue": "Conjunto de personas que cantan conjuntamente una pieza musical, sea de manera puntual o habitual"}, {"num": 46, "word": "COTO", "clue": "Mojón que se pone para señalar la división de los términos o de las heredades, y más propiamente el de piedra sin labrar"}, {"num": 47, "word": "AERITO", "clue": "Se dice de los animales que viven en el aire"}, {"num": 49, "word": "TREMAR", "clue": "Variante de tremer"}, {"num": 51, "word": "TORRERO", "clue": "Guardián de un faro"}, {"num": 55, "word": "AMABLE", "clue": "Digno de ser amado"}, {"num": 56, "word": "ACAECER", "clue": "Ocurrir, producirse un hecho, tener lugar un acontecimiento, suceder"}, {"num": 57, "word": "CEREAL", "clue": "En particular, fruto de estas plantas"}, {"num": 58, "word": "RAPSODA", "clue": "Persona que en la Grecia antigua iba de pueblo en pueblo cantando trozos de los poemas homéricos u otras poesías"}], "clues_v": [{"num": 1, "word": "MACADAM", "clue": "Pavimento de balasto (grava y piedra machacada) y bitumen (hormigón bituminoso), que una vez tendido se comprime con rodillo empapado en agua"}, {"num": 2, "word": "ACABADA", "clue": "Acción o efecto de acabar (eyacular)"}, {"num": 3, "word": "MINUTAS", "clue": "Escrita descripción de lo que ocurrió en una reunión"}, {"num": 4, "word": "BATEA", "clue": "Barco pequeño en figura de artesa, que se usa en los puertos y arsenales"}, {"num": 5, "word": "ORO", "clue": "Elemento químico con el número atómico 79. Es un metal pesado, dúctil, maleable, resistente a la corrosión, muy apreciado en joyería desde la remota Antigüedad"}, {"num": 6, "word": "CACHUZO", "clue": "Gastado o estropeado por el uso"}, {"num": 7, "word": "ACRON", "clue": "Región no segmentada de la parte anterior del cuerpo de un artrópodo"}, {"num": 8, "word": "PAIRAR", "clue": "Estar quieta la nave con las velas tendidas y largas las escotas; ponerse o estar al pairo"}, {"num": 9, "word": "ALAL", "clue": "Demonio destructor que, para tentar a los hombres, salía del infierno y adoptaba diversas formas; mientras que los caldeos lograban rechazar las tentaciones utilizando amuletos"}, {"num": 10, "word": "CODASTE", "clue": "Parte de la quilla de un barco donde termina la popa"}, {"num": 11, "word": "ERE", "clue": "Nombre de la letra r cuando tiene su sonido suave"}, {"num": 12, "word": "TAR", "clue": "Variante subestándar de estar"}, {"num": 13, "word": "ERO", "clue": "Conjunto de espacios de tierra, o tablas, destinados al cultivo de hortalizas"}, {"num": 19, "word": "CAIDO", "clue": "Que ha pasado"}, {"num": 23, "word": "POTITO", "clue": "Puré para bebés. Hay una plétora de variantes y sabores en el mercado para elegir"}, {"num": 24, "word": "ASADOR", "clue": "Aparato para asar comida"}, {"num": 25, "word": "MOROSO", "clue": "Que incurre en mora"}, {"num": 27, "word": "WARAO", "clue": "Propio de, relativo o perteneciente a una etnia amerindia que habita de forma transhumante el delta del río Orinoco"}, {"num": 29, "word": "ORAR", "clue": "Dirigir palabras o pensamientos hacia una divinidad u otra instancia metafísica superior para loarla, solicitar misericordia o dádivas, etc"}, {"num": 31, "word": "CANDOMBE", "clue": "Baile americano de ritmo muy vivo de origen negroafricano, de ritmo de cuatro negras por compás con clave 3:2, tradicional del Uruguay"}, {"num": 32, "word": "REPORTAR", "clue": "Contener, refrenar o reprimir"}, {"num": 36, "word": "TAPIOCA", "clue": "(Manihot esculenta) Fécula obtenida de la raíz de la mandioca con la que se hace una nutritiva sopa"}, {"num": 38, "word": "TICTAC", "clue": "Sonido que emite un reloj al mover las manecillas"}, {"num": 39, "word": "ENORME", "clue": "Grande en exceso"}, {"num": 40, "word": "ROTEAR", "clue": "Comportarse de forma grosera y maleducada"}, {"num": 41, "word": "ATE", "clue": "Dulce de membrillo en forma de barra o bloque a modo de dulce seco"}, {"num": 42, "word": "ACORES", "clue": "Ciertas úlceras que padecen los niños"}, {"num": 47, "word": "AREL", "clue": "Aquel que no ha pasado a formar parte del pueblo de Israel mediante el rito de la circuncisión"}, {"num": 48, "word": "TRAP", "clue": "Subgénero musical del rap que se originó en la década de los 90 en el sur de los Estados Unidos"}, {"num": 50, "word": "ALA", "clue": "Las alas son extremidades o apéndices que poseen algunos grupos de animales, normalmente utilizan estas alas para poder volar"}, {"num": 52, "word": "ECO", "clue": "Repetición del sonido causado por la reflexión de la onda sonora al chocar con una superficie rígida"}, {"num": 53, "word": "RED", "clue": "Malla cosa que fue creada para unir o sostener algo"}, {"num": 54, "word": "ORA", "clue": "Variante informal de ahora (en este momento, dentro de poco tiempo, hace poco tiempo, unas veces y otras)"}], "slots": [{"dir": "H", "num": 1, "cells": [[0, 0], [0, 1], [0, 2], [0, 3], [0, 4]]}, {"dir": "H", "num": 6, "cells": [[0, 6], [0, 7], [0, 8], [0, 9], [0, 10], [0, 11], [0, 12], [0, 13]]}, {"dir": "H", "num": 14, "cells": [[1, 0], [1, 1], [1, 2], [1, 3], [1, 4]]}, {"dir": "H", "num": 15, "cells": [[1, 6], [1, 7], [1, 8], [1, 9], [1, 10], [1, 11], [1, 12], [1, 13]]}, {"dir": "H", "num": 16, "cells": [[2, 0], [2, 1], [2, 2], [2, 3], [2, 4]]}, {"dir": "H", "num": 17, "cells": [[2, 6], [2, 7], [2, 8], [2, 9], [2, 10], [2, 11], [2, 12], [2, 13]]}, {"dir": "H", "num": 18, "cells": [[3, 0], [3, 1], [3, 2], [3, 3]]}, {"dir": "H", "num": 19, "cells": [[3, 5], [3, 6], [3, 7], [3, 8], [3, 9], [3, 10]]}, {"dir": "H", "num": 20, "cells": [[4, 0], [4, 1], [4, 2], [4, 3]]}, {"dir": "H", "num": 21, "cells": [[4, 5], [4, 6], [4, 7], [4, 8]]}, {"dir": "H", "num": 22, "cells": [[4, 10], [4, 11], [4, 12], [4, 13]]}, {"dir": "H", "num": 26, "cells": [[5, 0], [5, 1], [5, 2]]}, {"dir": "H", "num": 27, "cells": [[5, 4], [5, 5], [5, 6]]}, {"dir": "H", "num": 28, "cells": [[5, 8], [5, 9], [5, 10], [5, 11], [5, 12], [5, 13]]}, {"dir": "H", "num": 30, "cells": [[6, 0], [6, 1], [6, 2], [6, 3], [6, 4], [6, 5], [6, 6], [6, 7]]}, {"dir": "H", "num": 33, "cells": [[6, 9], [6, 10], [6, 11], [6, 12], [6, 13]]}, {"dir": "H", "num": 34, "cells": [[7, 3], [7, 4], [7, 5]]}, {"dir": "H", "num": 35, "cells": [[7, 7], [7, 8], [7, 9]]}, {"dir": "H", "num": 37, "cells": [[7, 11], [7, 12], [7, 13]]}, {"dir": "H", "num": 38, "cells": [[8, 0], [8, 1], [8, 2], [8, 3], [8, 4]]}, {"dir": "H", "num": 41, "cells": [[8, 6], [8, 7], [8, 8], [8, 9], [8, 10], [8, 11], [8, 12], [8, 13]]}, {"dir": "H", "num": 43, "cells": [[9, 0], [9, 1], [9, 2], [9, 3], [9, 4]]}, {"dir": "H", "num": 44, "cells": [[9, 6], [9, 7], [9, 8]]}, {"dir": "H", "num": 45, "cells": [[9, 10], [9, 11], [9, 12], [9, 13]]}, {"dir": "H", "num": 46, "cells": [[10, 0], [10, 1], [10, 2], [10, 3]]}, {"dir": "H", "num": 47, "cells": [[10, 5], [10, 6], [10, 7], [10, 8], [10, 9], [10, 10]]}, {"dir": "H", "num": 49, "cells": [[11, 0], [11, 1], [11, 2], [11, 3], [11, 4], [11, 5]]}, {"dir": "H", "num": 51, "cells": [[11, 7], [11, 8], [11, 9], [11, 10], [11, 11], [11, 12], [11, 13]]}, {"dir": "H", "num": 55, "cells": [[12, 0], [12, 1], [12, 2], [12, 3], [12, 4], [12, 5]]}, {"dir": "H", "num": 56, "cells": [[12, 7], [12, 8], [12, 9], [12, 10], [12, 11], [12, 12], [12, 13]]}, {"dir": "H", "num": 57, "cells": [[13, 0], [13, 1], [13, 2], [13, 3], [13, 4], [13, 5]]}, {"dir": "H", "num": 58, "cells": [[13, 7], [13, 8], [13, 9], [13, 10], [13, 11], [13, 12], [13, 13]]}, {"dir": "V", "num": 1, "cells": [[0, 0], [1, 0], [2, 0], [3, 0], [4, 0], [5, 0], [6, 0]]}, {"dir": "V", "num": 38, "cells": [[8, 0], [9, 0], [10, 0], [11, 0], [12, 0], [13, 0]]}, {"dir": "V", "num": 2, "cells": [[0, 1], [1, 1], [2, 1], [3, 1], [4, 1], [5, 1], [6, 1]]}, {"dir": "V", "num": 39, "cells": [[8, 1], [9, 1], [10, 1], [11, 1], [12, 1], [13, 1]]}, {"dir": "V", "num": 3, "cells": [[0, 2], [1, 2], [2, 2], [3, 2], [4, 2], [5, 2], [6, 2]]}, {"dir": "V", "num": 40, "cells": [[8, 2], [9, 2], [10, 2], [11, 2], [12, 2], [13, 2]]}, {"dir": "V", "num": 4, "cells": [[0, 3], [1, 3], [2, 3], [3, 3], [4, 3]]}, {"dir": "V", "num": 31, "cells": [[6, 3], [7, 3], [8, 3], [9, 3], [10, 3], [11, 3], [12, 3], [13, 3]]}, {"dir": "V", "num": 5, "cells": [[0, 4], [1, 4], [2, 4]]}, {"dir": "V", "num": 27, "cells": [[5, 4], [6, 4], [7, 4], [8, 4], [9, 4]]}, {"dir": "V", "num": 50, "cells": [[11, 4], [12, 4], [13, 4]]}, {"dir": "V", "num": 19, "cells": [[3, 5], [4, 5], [5, 5], [6, 5], [7, 5]]}, {"dir": "V", "num": 47, "cells": [[10, 5], [11, 5], [12, 5], [13, 5]]}, {"dir": "V", "num": 6, "cells": [[0, 6], [1, 6], [2, 6], [3, 6], [4, 6], [5, 6], [6, 6]]}, {"dir": "V", "num": 41, "cells": [[8, 6], [9, 6], [10, 6]]}, {"dir": "V", "num": 7, "cells": [[0, 7], [1, 7], [2, 7], [3, 7], [4, 7]]}, {"dir": "V", "num": 32, "cells": [[6, 7], [7, 7], [8, 7], [9, 7], [10, 7], [11, 7], [12, 7], [13, 7]]}, {"dir": "V", "num": 8, "cells": [[0, 8], [1, 8], [2, 8], [3, 8], [4, 8], [5, 8]]}, {"dir": "V", "num": 36, "cells": [[7, 8], [8, 8], [9, 8], [10, 8], [11, 8], [12, 8], [13, 8]]}, {"dir": "V", "num": 9, "cells": [[0, 9], [1, 9], [2, 9], [3, 9]]}, {"dir": "V", "num": 29, "cells": [[5, 9], [6, 9], [7, 9], [8, 9]]}, {"dir": "V", "num": 48, "cells": [[10, 9], [11, 9], [12, 9], [13, 9]]}, {"dir": "V", "num": 10, "cells": [[0, 10], [1, 10], [2, 10], [3, 10], [4, 10], [5, 10], [6, 10]]}, {"dir": "V", "num": 42, "cells": [[8, 10], [9, 10], [10, 10], [11, 10], [12, 10], [13, 10]]}, {"dir": "V", "num": 11, "cells": [[0, 11], [1, 11], [2, 11]]}, {"dir": "V", "num": 23, "cells": [[4, 11], [5, 11], [6, 11], [7, 11], [8, 11], [9, 11]]}, {"dir": "V", "num": 52, "cells": [[11, 11], [12, 11], [13, 11]]}, {"dir": "V", "num": 12, "cells": [[0, 12], [1, 12], [2, 12]]}, {"dir": "V", "num": 24, "cells": [[4, 12], [5, 12], [6, 12], [7, 12], [8, 12], [9, 12]]}, {"dir": "V", "num": 53, "cells": [[11, 12], [12, 12], [13, 12]]}, {"dir": "V", "num": 13, "cells": [[0, 13], [1, 13], [2, 13]]}, {"dir": "V", "num": 25, "cells": [[4, 13], [5, 13], [6, 13], [7, 13], [8, 13], [9, 13]]}, {"dir": "V", "num": 54, "cells": [[11, 13], [12, 13], [13, 13]]}]}